validata/__init__.py
validata/version.py
validata/checks/__init__.py
validata/checks/clear_rows.py
validata/checks/columns.py
validata/checks/distinct_values.py
validata/checks/extract_months.py
validata/checks/month_utils.py
validata/checks/month_validation.py
validata/checks/required_columns.py
validata/checks/required_missing.py
validata/checks/value_counts.py
validata/io/__init__.py
validata/io/loader.py
validata/utils/__init__.py
validatax-0.2.0.dist-info/licenses/LICENSE
validatax-0.2.0.dist-info/METADATA
validatax-0.2.0.dist-info/WHEEL
validatax-0.2.0.dist-info/top_level.txt
validatax-0.2.0.dist-info/RECORD
