Metadata-Version: 2.4
Name: validatax
Version: 0.2.0
Summary: A lightweight data validation toolkit
Author-email: sumith <sumithsingh558@gmail.com>
License: MIT
Project-URL: Homepage, https://github.com/sumith/validata
Project-URL: Source, https://github.com/sumith/validata
Keywords: data-quality,validation,pandas,schema,columns
Requires-Python: >=3.10
License-File: LICENSE
Requires-Dist: pandas>=1.5
Requires-Dist: openpyxl>=3.1
Dynamic: license-file
